odoo/addons/l10n_br_hr_expense_invoice/README.rst
odoo/addons/l10n_br_hr_expense_invoice/__init__.py
odoo/addons/l10n_br_hr_expense_invoice/__manifest__.py
odoo/addons/l10n_br_hr_expense_invoice/i18n/l10n_br_hr_expense_invoice.pot
odoo/addons/l10n_br_hr_expense_invoice/i18n/pt_BR.po
odoo/addons/l10n_br_hr_expense_invoice/models/__init__.py
odoo/addons/l10n_br_hr_expense_invoice/models/hr_expense.py
odoo/addons/l10n_br_hr_expense_invoice/models/res_company.py
odoo/addons/l10n_br_hr_expense_invoice/readme/CONTRIBUTORS.md
odoo/addons/l10n_br_hr_expense_invoice/readme/DESCRIPTION.md
odoo/addons/l10n_br_hr_expense_invoice/readme/USAGE.md
odoo/addons/l10n_br_hr_expense_invoice/static/description/icon.png
odoo/addons/l10n_br_hr_expense_invoice/static/description/index.html
odoo/addons/l10n_br_hr_expense_invoice/tests/__init__.py
odoo/addons/l10n_br_hr_expense_invoice/tests/test_l10n_br_hr_expense_invoice.py
odoo/addons/l10n_br_hr_expense_invoice/views/hr_expense_sheet.xml
odoo/addons/l10n_br_hr_expense_invoice/views/res_company.xml
odoo_addon_l10n_br_hr_expense_invoice-16.0.1.0.1.2.dist-info/METADATA
odoo_addon_l10n_br_hr_expense_invoice-16.0.1.0.1.2.dist-info/WHEEL
odoo_addon_l10n_br_hr_expense_invoice-16.0.1.0.1.2.dist-info/top_level.txt
odoo_addon_l10n_br_hr_expense_invoice-16.0.1.0.1.2.dist-info/RECORD
