Metadata-Version: 2.1
Name: odoo-addon-l10n_br_hr_expense_invoice
Version: 16.0.1.0.1.2
Requires-Python: >=3.10
Requires-Dist: odoo-addon-hr_expense_invoice>=16.0dev,<16.1dev
Requires-Dist: odoo-addon-l10n_br_fiscal>=16.0dev,<16.1dev
Requires-Dist: odoo>=16.0a,<16.1dev
Summary: Customization of HR Expense Invoice module for implementations in Brazil.
Home-page: https://github.com/OCA/l10n-brazil
License: AGPL-3
Author: Escodoo,Odoo Community Association (OCA)
Author-email: support@odoo-community.org
Classifier: Programming Language :: Python
Classifier: Framework :: Odoo
Classifier: Framework :: Odoo :: 16.0
Classifier: License :: OSI Approved :: GNU Affero General Public License v3
